hloc/__init__.py
hloc/colmap_from_nvm.py
hloc/extract_features.py
hloc/gaussian_eval.py
hloc/localize_inloc.py
hloc/localize_sfm.py
hloc/match_features.py
hloc/pairs_from_covisibility.py
hloc/pairs_from_exhaustive.py
hloc/pairs_from_poses.py
hloc/pairs_from_retrieval.py
hloc/reconstruction.py
hloc/triangulation.py
hloc/visualization.py
hloc_mod/__init__.py
hloc_mod/colmap_from_nvm.py
hloc_mod/extract_features.py
hloc_mod/gaussian_eval.py
hloc_mod/localize_inloc.py
hloc_mod/localize_sfm.py
hloc_mod/match_features.py
hloc_mod/pairs_from_covisibility.py
hloc_mod/pairs_from_exhaustive.py
hloc_mod/pairs_from_poses.py
hloc_mod/pairs_from_retrieval.py
hloc_mod/reconstruction.py
hloc_mod/triangulation.py
hloc_mod/visualization.py
hloc_mod-1.5.dist-info/LICENSE
hloc_mod-1.5.dist-info/METADATA
hloc_mod-1.5.dist-info/WHEEL
hloc_mod-1.5.dist-info/top_level.txt
hloc_mod-1.5.dist-info/RECORD
