Metadata-Version: 2.1
Name: hloc-mod
Version: 1.5
Summary: ['Tools and baselines for visual localization and mapping']
Home-page: UNKNOWN
Author: Paul-Edouard Sarlin, XINLI
License: UNKNOWN
Platform: UNKNOWN
Classifier: Programming Language :: Python :: 3
Classifier: License :: OSI Approved :: Apache Software License
Classifier: Operating System :: OS Independent
Requires-Python: >=3.6
License-File: LICENSE
Requires-Dist: torch (>=1.1)
Requires-Dist: torchvision (>=0.3)
Requires-Dist: numpy
Requires-Dist: opencv-python
Requires-Dist: tqdm (>=4.36.0)
Requires-Dist: matplotlib
Requires-Dist: plotly
Requires-Dist: scipy
Requires-Dist: h5py
Requires-Dist: pycolmap (>=0.1.0)
Requires-Dist: kornia
